[
    {
        "id_str": "775473823047118848",
        "text": "おはようございます☀︎\n\n#coconutoilcoffee #diet #morning #早上好 #안녕하세요 https://t.co/uQ8g8vGke9",
        "trans": ""
    },
    {
        "id_str": "775408898350026752",
        "text": "【オリコン】HKT48、デビューから8作連続首位　女性歌手トップ独走（写真 全2枚）\nhttps://t.co/tRKgo9pocM\n\n #オリコン #HKT48 #松岡はな #音楽 #ニュース",
        "trans": ""
    },
    {
        "id_str": "775484624390590464",
        "text": "感謝でいっぱいです。\n本当に、いろんな方に支えられ、見守ってもらいながら進んできました。\nさっしー、あいちゃん、先輩方にも...\nあの景色をもう1度！今のHKT48で！\n下半期も突っ走るぞ〜！！\n応援よろしくお願いします☺️ https://t.co/Si40u3Dfgt",
        "trans": ""
    },
    {
        "id_str": "775679279048773632",
        "text": "@haruka_kdm919 \nはるっぴフォロワー７万人おめでとう😍👏💖",
        "trans": ""
    },
    {
        "id_str": "775709711429570560",
        "text": "@ParU48salt ほんとだ☺️💓\nフォローありがとうございまーす！",
        "trans": ""
    }
]