{
    "id": "z12rdlehkynywr4jd04chnsp3zbfxjwahho",
    "published": "2011-12-14 18:36:08.257",
    "updated": "2011-12-14 18:36:08.257",
    "description": "HKT48 兒玉遥です\n\nこんにちは☆\n\nもう少しで公演です!!\n\n今日は皆さんと\nたくさん目を合わせることを目標に歌って踊ります＼(^o^)／\n\n頑張るっぴ★\n行ってきます。\n\nはるっぴ。o∮(・∀...",
    "content": "HKT48 兒玉遥です<br /><br />こんにちは☆<br /><br />もう少しで公演です!!<br /><br />今日は皆さんと<br />たくさん目を合わせることを目標に歌って踊ります＼(^o^)／<br /><br />頑張るっぴ★<br />行ってきます。<br /><br />はるっぴ。o∮(・∀・)∮o。＊ルルルーン♪﻿",
    "url": "https://plus.google.com/106758056094193397775/posts/fzj4w1UMqxh",
    "images": [
        "https://lh4.googleusercontent.com/-KW_v-EIAGBI/TuhuA0IAcmI/AAAAAAAAz0g/eWjmhPwA6co/w288-h288/41u.jpg"
    ],
    "videos": []
}