{
    "id": "z12jenfgjpvixlgkk23gy5cztuzfz1nfh",
    "published": "2011-12-19 22:13:23.825",
    "updated": "2011-12-19 22:13:23.825",
    "description": "HKT48兒玉遥\n\n\nこんにちは。\n昨日もたくさんのコメントありがとうございました☆\n\n『はるっぴから元気をもらってるよ。』などと言われすごく嬉しくなりました。\n\n私も皆さんの言葉で\nまたHappy☆...",
    "content": "HKT48兒玉遥<br /><br /><br />こんにちは。<br />昨日もたくさんのコメントありがとうございました☆<br /><br />『はるっぴから元気をもらってるよ。』などと言われすごく嬉しくなりました。<br /><br />私も皆さんの言葉で<br />またHappy☆になれます<br /><br />この感謝の気持ちを込めて<br />今から全力で歌って踊ります!!<br /><br />行って参ります(*＾*)／<br /><br />はるっぴ。o∮(・∀・)∮o。＊ルルルーン♪﻿",
    "url": "https://plus.google.com/106758056094193397775/posts/3k4c1naEyv5",
    "images": [],
    "videos": []
}