{
    "id": "z12qzx3ywqidtpnap04cdtnarqepc1uqt0w",
    "published": "2014-09-25 17:44:27.301",
    "updated": "2014-09-25 17:44:27.301",
    "description": "皆さん、こんにちは＼(^o^)／\n\n\nレコーディングしていました！！\n\n\nみんなの中でも\n皆さんに届くようにって歌ったよ。\n\n\n\nこれから撮影がんばるぞー♪",
    "content": "皆さん、こんにちは＼(^o^)／<br /><br /><br />レコーディングしていました！！<br /><br /><br />みんなの中でも<br />皆さんに届くようにって歌ったよ。<br /><br /><br /><br />これから撮影がんばるぞー♪﻿",
    "url": "https://plus.google.com/111907069956262615426/posts/cj9G6WCKETN",
    "images": [
        "https://lh6.googleusercontent.com/-leJuWc-ecco/VCPV6n9MxzI/AAAAAAAXROM/Tu70vB4dVWc/w240-h320/25%2B-%2B1"
    ],
    "videos": []
}