{
    "id": "z12tdrbx4w3ecdnsb22igtpxmpe0ipqcb",
    "published": "2013-12-12 18:26:28.600",
    "updated": "2013-12-12 18:26:28.600",
    "description": "東京ついたよ(^○^)\n\n今日泊まるホテルが\nなんかすごいらしい…(゜ロ゜;\n\n良い意味かと思ったら\n逆だったの。。\n\nどんな感じだろう？\n\nせめて、シャワーから\nお湯が出てほしいな♪\n\nドキドキして...",
    "content": "東京ついたよ(^○^)<br /><br />今日泊まるホテルが<br />なんかすごいらしい…(゜ロ゜;<br /><br />良い意味かと思ったら<br />逆だったの。。<br /><br />どんな感じだろう？<br /><br />せめて、シャワーから<br />お湯が出てほしいな♪<br /><br />ドキドキしてますf(^_^;<br /><br />﻿",
    "url": "https://plus.google.com/111907069956262615426/posts/2Gu9Jn2LG6D",
    "images": [],
    "videos": []
}