{
    "id": "z13jcnvixrbjdfkwj04cdtnarqepc1uqt0w",
    "published": "2014-10-11 23:43:58.418",
    "updated": "2014-10-11 23:43:58.418",
    "description": "こんばんは^_−☆\n\n\nお家に帰ると、弟二人が\n『妖怪ウォッチ』の魅力を語っていました。\n\n\nヨーデルヨーデル…♪\n私もハマっちゃいそうだなぁ！！\n\n\n明日、なこに踊り教えてもらお(^ー゜)\n\n\n二回...",
    "content": "こんばんは^_−☆<br /><br /><br />お家に帰ると、弟二人が<br />『妖怪ウォッチ』の魅力を語っていました。<br /><br /><br />ヨーデルヨーデル…♪<br />私もハマっちゃいそうだなぁ！！<br /><br /><br />明日、なこに踊り教えてもらお(^ー゜)<br /><br /><br />二回公演に備えまして<br />もう、寝るとします。<br /><br /><br />おやすみなさい。<br />ぷひゅーはー☆ミ<br /><br /><br /><br /><br />﻿",
    "url": "https://plus.google.com/111907069956262615426/posts/R1NTgRQwjs3",
    "images": [
        "https://lh4.googleusercontent.com/-y0BliSodXls/VDlCLfUNDLI/AAAAAAAXRYs/sYWpLBJlHBA/w452-h620/11%2B-%2B1"
    ],
    "videos": []
}