{
    "published": "2011-12-18 17:06:22.128",
    "updated": "2011-12-18 17:06:22.128",
    "description": "HKT48 兒玉遥\n\nこんにちは。\n\nムービーを撮っていたら\nういたんが乱入してきました！！\n\n私を探してくれてたみたいです＼(^o^)／\n\n嬉しいなぁ(>∀<)y-~\n\n公演頑張ってきます☆\n\nはるっぴ...",
    "content": "HKT48 兒玉遥<br /> <br />こんにちは。<br /><br />ムービーを撮っていたら<br />ういたんが乱入してきました！！<br /><br />私を探してくれてたみたいです＼(^o^)／<br /><br />嬉しいなぁ(&gt;∀&lt;)y-~<br /><br />公演頑張ってきます☆<br /><br />はるっぴ。o∮(・∀・)∮o。＊ルルルーン♪﻿",
    "url": "https://plus.google.com/106758056094193397775/posts/2nYAeCnjKrS",
    "images": [],
    "videos": [
        "https://lh6.googleusercontent.com/-DssXgSLnFDw/Tu2eGe4na4I/AAAAAAABzPg/jSXkVOhME7A/w506-h379-o/%25E5%2585%2592%25E7%258E%2589%25E9%2581%25A55.mp4"
    ]
}