{
    "published": "2012-11-28 21:08:59.166",
    "updated": "2012-11-28 21:08:59.166",
    "description": "あいちゃんとなつと私で\n大砲ラーメン行ったんだぁ＼(^o^)／\n\n大砲ラーメン\nずっと食べたかったの♪\n\n久留米出身の豚骨ラーメン!!\n\n私は硬麺派。\n\n\n味は博多のラーメンと比べると\nあさっりしてる...",
    "content": "あいちゃんとなつと私で<br />大砲ラーメン行ったんだぁ＼(^o^)／<br /><br />大砲ラーメン<br />ずっと食べたかったの♪<br /><br />久留米出身の豚骨ラーメン!!<br /><br />私は硬麺派。<br /><br /><br />味は博多のラーメンと比べると<br />あさっりしてるように感じました。<br /><br />しっかり味の詰まったスープなのに<br />程よいコクでコッテリし過ぎず<br />食べやすかったです(๑ت๑)<br /><br />他のラーメン屋さんより<br />多い感じの細麺も全然飽きないです。<br /><br /><br />美味しいラーメンでしたฅ^•ω•^ฅ<br /><br />機会があったら是非<br />行ってみてください♪<br /><br /><br />私は本当にラーメンが大好きで<br />特に博多の豚骨が好きっちゃん。<br /><br />まだまだ行けていないラーメン屋さんが沢山あるけん<br />全件制覇したいなぁ…<br /><br />なんて思ったり(๑°ﾛ °๑)<br /><br />ラーメントーク今度してみましょっ✌<br /><br />はるっぴのラーメンレポートでした!!<br /><br />どうでしたか？<br />美味しさ伝わりましたか？﻿",
    "url": "https://plus.google.com/111907069956262615426/posts/8nPFq75Ztxf",
    "images": [
        "https://lh6.googleusercontent.com/-aBEOz0Qtw30/ULX-2qZCFqI/AAAAAAACg7c/xAzxeliNB8k/s0-d/28%2B-%2B1"
    ],
    "videos": []
}