{
    "published": "2012-04-13 21:27:43.303",
    "updated": "2012-04-13 21:27:43.303",
    "description": "公演終わりました！\n\nアーニャと\nほっぺたスキンシップした(>∀<)\n\n画像…\n\n\nアーニャ(村重杏奈)のグクタスで\n撮ったんだった…\n\n\nおーい\nUPしてくれー\n\nホントにフニフニ♪\n決して変態なんか...",
    "content": "公演終わりました！<br /><br />アーニャと<br />ほっぺたスキンシップした(&gt;∀&lt;)<br /><br />画像…<br /><br /><br />アーニャ(村重杏奈)のグクタスで<br />撮ったんだった…<br /><br /><br />おーい<br />UPしてくれー<br /><br />ホントにフニフニ♪<br />決して変態なんかじゃないもんね！<br /><br />…うん。<br /><br /><br />アーニャのほっぺた大好き＼(^o^)／<br />もちろんアーニャも…<br /><br /><br /><br /><br /><br />大好きよ。<br /><br />あれ？<br />何言ってんだろ私。<br /><br />﻿",
    "url": "https://plus.google.com/111907069956262615426/posts/KJVSnDqBkLB",
    "images": [],
    "videos": []
}