{
    "published": "2012-08-18 21:17:26.675",
    "updated": "2012-08-18 21:17:26.675",
    "description": "皆さん\nコメントありがとうございます!!\n\nこんなにもたくさん方々が\n私達のことを応援、心配してくださってることを知って\nとても嬉しかったです。\n\n\n支えてくださる皆さんのために\nHKT48のために\n...",
    "content": "<br />皆さん<br />コメントありがとうございます!!<br /><br />こんなにもたくさん方々が<br />私達のことを応援、心配してくださってることを知って<br />とても嬉しかったです。<br /><br /><br />支えてくださる皆さんのために<br />HKT48のために<br />先輩方のために<br />自分自身のために…<br /><br />改めて、今<br />今しかないこの時間を<br />もっと頑張らなきゃな<br />努力しなきゃなと思わされました。<br /><br /><br />よろしくお願いします!!﻿",
    "url": "https://plus.google.com/111907069956262615426/posts/ZokQdYYatTR",
    "images": [],
    "videos": []
}