{
    "published": "2013-06-17 18:43:54.337",
    "updated": "2013-06-17 18:43:54.337",
    "description": "この前の『HKT48のおでかけ』で\nおでセン(=おでかけセンター)総選挙で\n谷が一位で\n私がめると４位やったけど\nおでこセンターの\nおでセンやったら一位だもーん( ˙³˙)♪",
    "content": "この前の『HKT48のおでかけ』で<br />おでセン(=おでかけセンター)総選挙で<br />谷が一位で<br />私がめると４位やったけど<br />おでこセンターの<br />おでセンやったら一位だもーん( ˙³˙)♪<br />﻿",
    "url": "https://plus.google.com/111907069956262615426/posts/Ujk43iK7YSg",
    "images": [
        "https://lh4.googleusercontent.com/-LLOkYwKFokc/Ub7aWRkonzI/AAAAAAAXOmU/aCmpqJfmWJQ/w960-h1280/17%2B-%2B1"
    ],
    "videos": []
}