{
    "published": "2013-10-06 22:14:30.607",
    "updated": "2013-10-06 22:14:30.607",
    "description": "久しぶりにわるっぴ降臨！！！！\n\nお母さんが\nなんの祝いの日でもないのに\nチーズスフレケーキと生チョコケーキ\n2ホール買ってきた󾌧󾌧󾌧󾌧󾌧ﾜｰｲ\n\n家族みんなで美味しそうに食べてる。\n\nそして...",
    "content": "久しぶりにわるっぴ降臨！！！！<br /><br />お母さんが<br />なんの祝いの日でもないのに<br />チーズスフレケーキと生チョコケーキ<br />2ホール買ってきた󾌧󾌧󾌧󾌧󾌧ﾜｰｲ<br /><br />家族みんなで美味しそうに食べてる。<br /><br />そして、わるっぴが言う。<br />「そんなに食べたいなら食べちゃえよ！！」<br /><br />はるっぴ<br />『で、でもこんな時間に食べたらデブだよ！！』<br /><br />「一日くらいたいして変わらないでしよ(ー_ー)!!」<br /><br />わーーーーーっぅ󾭛<br /><br />どうぴよ？？？﻿",
    "url": "https://plus.google.com/111907069956262615426/posts/D4HdvN59P8y",
    "images": [
        "https://lh6.googleusercontent.com/-cTwpl9Xw1gs/UlFiNWmzzkI/AAAAAAALeus/4GzVVe3C3uw/w960-h1280/06%2B-%2B1"
    ],
    "videos": []
}