{
    "published": "2013-09-29 21:38:39.124",
    "updated": "2013-09-29 21:38:39.124",
    "description": "家族で腕相撲大会したっちゃんヽ(´▽｀)/\n\n私は家族で4位でした(゜ロ゜)\n\n弟の長男の方が\nダントツで一位󾭠\n\nお父さんは負けて悔しがってました！笑\n\n私もお母さんに勝てなくて\n悔しかった󾌣\n...",
    "content": "家族で腕相撲大会したっちゃんヽ(´▽｀)/<br /><br />私は家族で4位でした(゜ロ゜)<br /><br />弟の長男の方が<br />ダントツで一位󾭠<br /><br />お父さんは負けて悔しがってました！笑<br /><br />私もお母さんに勝てなくて<br />悔しかった󾌣<br /><br />まだまだお母さんには<br />かなわないや！<br /><br />プチパーティーみたいで<br />楽しかった♪<br /><br />最近、東京いってて<br />あまり家にいないから<br />こうやってみんなで揃った時に<br />幸せだなー<br />落ち着くなーって感じます(｡･･｡)<br />﻿",
    "url": "https://plus.google.com/111907069956262615426/posts/fECCcaAiU5r",
    "images": [
        "https://lh6.googleusercontent.com/-PB32Wn-UMTs/UkgfTijfmMI/AAAAAAALMmk/i7sB3SUCW6k/w960-h1280/29%2B-%2B1"
    ],
    "videos": []
}