{
    "published": "2013-08-24 18:49:08.024",
    "updated": "2013-08-24 18:52:20.000",
    "descript": "玲奈さん＼(^o^)／\n\n可愛いーーっ♡\n美しいーーっ♪\nきゃぴきゃぴしてる！！\nずっと見ていたい！！\n\n良いなぁ。\n私も世界を飛び回る人になるのが目標でもあるから\n頑張ります。\n\n玲奈さんと一緒に\n...",
    "content": "玲奈さん＼(^o^)／<br /><br />可愛いーーっ♡<br />美しいーーっ♪<br />きゃぴきゃぴしてる！！<br />ずっと見ていたい！！<br /><br />良いなぁ。<br />私も世界を飛び回る人になるのが目標でもあるから<br />頑張ります。<br /><br />玲奈さんと一緒に<br />ディズニーランド行きたいなぁ(o´罒`o)﻿",
    "url": "https://plus.google.com/111907069956262615426/posts/cxL5rhqmZjP",
    "images": [
        "https://lh6.googleusercontent.com/-tvD1SWKliRE/Uhirw_1mbxI/AAAAAAAJdzw/H00nQtubO3I/s288/photo.jpg"
    ]
}