{
    "published": "2013-02-24 23:20:01.771",
    "updated": "2013-02-24 23:20:01.771",
    "description": "こんばんは。兒玉遥です(*^^)v\n\n今日はステージで\n曲通しのレッスンをしたっちゃん。\n\nレッスン場は鏡があって安心しとるけど\nやっぱりステージに立つと\n不安要素が色々出てきて\n自分の課題を発見できる...",
    "content": "こんばんは。兒玉遥です(*^^)v<br /><br />今日はステージで<br />曲通しのレッスンをしたっちゃん。<br /><br />レッスン場は鏡があって安心しとるけど<br />やっぱりステージに立つと<br />不安要素が色々出てきて<br />自分の課題を発見できる。<br /><br />練習は100%でしても<br />本番って70%くらいしか出せないって<br />中学で部活してる時に教わったっちゃん。<br /><br />やけん、練習は失敗を恐れず<br />130%の気持ちでせんとね(<b>˘︶˘</b>)<br /><br />失敗は成功のもとって言うし。<br />逆を言えば『成功は失敗の証』。<br /><br /><br />残りあと4日✌<br />よっしゃー！頑張るけーん(ง •̀_•́)ง<br /><br />おやすみなさい。<br />ぷひゅーはー( ˙³˙)( ˙³˙)( ˙³˙)<br /><br /><br />今日は『ぷひゅーはー』動画です。<br /><br />﻿",
    "url": "https://plus.google.com/111907069956262615426/posts/1A3gv8aq6JL",
    "images": [],
    "videos": [
        "https://lh4.googleusercontent.com/-mJwF_RpCbjs/USohkLvlEiI/AAAAAAADlMg/kT6j1oEBoIs/w506-h379-n-o/20130224_110822.mp4"
    ]
}