{
    "published": "2014-04-12 18:54:53.585",
    "updated": "2014-04-12 18:54:53.585",
    "descript": "いつかの私服(｡-_-｡)\n\n\n白のニットは\n合わせやすいから好き♡\n\n\nギンガムチェックのスカートも\n気に入ってるよ！",
    "content": "いつかの私服(｡-_-｡)<br /><br /><br />白のニットは<br />合わせやすいから好き♡<br /><br /><br />ギンガムチェックのスカートも<br />気に入ってるよ！﻿",
    "url": "https://plus.google.com/111907069956262615426/posts/URv2QbSY6E8",
    "images": [
        "https://lh5.googleusercontent.com/-id6AetuTQhg/U0k3nBejmHI/AAAAAAASR1Q/fjj7tEwI3rc/w960-h1280/12%2B-%2B1"
    ]
}