{
    "published": "2014-03-09 16:48:48.526",
    "updated": "2014-03-09 16:48:48.526",
    "description": "撮影してましたー＼(^^)／\n\nそれにしても、今日は寒い！\n\nさっき、ちょぴっと外に出たんやけど\n真っ赤のお鼻のトナカイさんみたいに…\n\nさぶいよー。\n\n福岡でこれだけ寒かったら\n東の方はもっと寒いの...",
    "content": "撮影してましたー＼(^^)／<br /><br />それにしても、今日は寒い！<br /><br />さっき、ちょぴっと外に出たんやけど<br />真っ赤のお鼻のトナカイさんみたいに…<br /><br />さぶいよー。<br /><br />福岡でこれだけ寒かったら<br />東の方はもっと寒いのかな？？<br /><br />皆さん、気をつけてくださいね(´∇｀)﻿",
    "url": "https://plus.google.com/111907069956262615426/posts/8hPX4rGPKxy",
    "images": [
        "https://lh5.googleusercontent.com/-CNNghbey9vU/Uxwc32Shq-I/AAAAAAARB4c/DafK2ZVPkXs/w853-h1280/08%2B-%2B1"
    ],
    "videos": []
}