{
    "published": "2014-08-22 17:08:03.685",
    "updated": "2014-08-22 17:12:30.000",
    "descript": "今日の私服＼(^o^)／\n\n\nいっぱい歩くときは\nパンツスタイルでいることが多いです。\n\n\nこの、ゆるめのデニムは\nなんにでも合わせやすいからヘビロテしてます♡\n\n\n\n\n感想まっとうけーん！﻿",
    "content": "今日の私服＼(^o^)／<br /><br /><br />いっぱい歩くときは<br />パンツスタイルでいることが多いです。<br /><br /><br />この、ゆるめのデニムは<br />なんにでも合わせやすいからヘビロテしてます♡<br /><br /><br /><br /><br />感想まっとうけーん！﻿",
    "url": "https://plus.google.com/111907069956262615426/posts/bvG7crstn5e",
    "images": [
        "https://lh5.googleusercontent.com/-hzvh-bpQO1o/U_ckkt-7ZjI/AAAAAAAXNx8/1kgi-94poN0/w756-h1280/22%2B-%2B1"
    ]
}