{
    "published": "2014-07-01 19:15:27.588",
    "updated": "2014-07-01 19:17:40.000",
    "description": "今日は、東京で一仕事終えてから時間があったので\n念願の１人ブラブラをしてきましたー＼(^o^)／\n\n\n自由が丘のサロンにいったついでに\n気になってる\nアサイーボウルを食べてきました♪\n\n\n美味しかったぁ...",
    "content": "今日は、東京で一仕事終えてから時間があったので<br />念願の１人ブラブラをしてきましたー＼(^o^)／<br /><br /><br />自由が丘のサロンにいったついでに<br />気になってる<br />アサイーボウルを食べてきました♪<br /><br /><br />美味しかったぁ！！<br /><br /><br />自由が丘って<br />丘が沢山あるから  <br />自由が丘っていうんですね(^o^)<br /><br />運転手の方から<br />教えていただきました！<br /><br />丘が沢山！！<br /><br />メモメモ…<br /><br />東京は、一駅、一駅に<br />街があってすごいなぁって思います。<br /><br />楽しいから<br />いっぱい開拓していきたいなぁ＼(^o^)／﻿",
    "url": "https://plus.google.com/111907069956262615426/posts/MotjfZ3wTGd",
    "images": [
        "https://lh6.googleusercontent.com/-ai7HshROUFA/U7KKPuQBYPI/AAAAAAAVeT8/NMcTSuESFzQ/w770-h1280/01%2B-%2B1"
    ],
    "videos": []
}