{
    "published": "2014-05-10 21:48:21.358",
    "updated": "2014-05-10 21:48:21.358",
    "description": "こんばんはー♪\n\nHKT48チームK4兼任の花音さんと\nちょっくら、レッスンしとりましたヽ(´▽`)ﾉ\n\nますます、明日のガイシが楽しみです！！\n\nそして、今日の私服♡\n\nブルーのギンガムチェックのシャツ...",
    "content": "こんばんはー♪<br /><br />HKT48チームK4兼任の花音さんと<br />ちょっくら、レッスンしとりましたヽ(´▽`)ﾉ<br /><br />ますます、明日のガイシが楽しみです！！<br /><br />そして、今日の私服♡<br /><br />ブルーのギンガムチェックのシャツに<br />白のスカート。<br /><br />すっかり夏気分です(〃▽〃)﻿",
    "url": "https://plus.google.com/111907069956262615426/posts/XmQEYkhRGoa",
    "images": [
        "https://lh3.googleusercontent.com/-3-Ji3IgX_Rk/U24gFB_g3_I/AAAAAAATQrg/3H9TYa5kgrA/w960-h1280/10%2B-%2B1"
    ],
    "videos": []
}