{
    "published": "2014-11-01 20:09:36.381",
    "updated": "2014-11-01 21:56:50.000",
    "descript": "こんばんは^_−☆\n\n\nもう、こんな時間。\n毎日、今日があっという間に終わっちゃいます。\n\n\n帰宅して、自分の部屋に入ると\n朝起きて着替えたのがついさっきのようです…\n\n\n楽しい時間って本当にあっという間...",
    "content": "こんばんは^_−☆<br /><br /><br />もう、こんな時間。<br />毎日、今日があっという間に終わっちゃいます。<br /><br /><br />帰宅して、自分の部屋に入ると<br />朝起きて着替えたのがついさっきのようです…<br /><br /><br />楽しい時間って本当にあっという間。<br /><br /><br />ライブなんて一瞬にしてアンコールになっちゃう。<br /><br /><br />毎日、楽しいことを思う存分しながら過ごせていること、<br />幸せですね(￣▽￣)<br /><br /><br />今日も1日<br />ありがとうございました！！<br /><br /><br />皆さんは、どんな三連休を過ごしてますか？<br /><br /><br />おやすみなさい。<br />ぷひゅーはー☆ミ<br /><br />﻿",
    "url": "https://plus.google.com/111907069956262615426/posts/jWMJMzXsff2",
    "images": [
        "https://lh6.googleusercontent.com/-KuiQJY2LujY/VFTpnrxDHoI/AAAAAAAXSUw/415uDwPzOKg/w480-h640/01%2B-%2B1"
    ]
}