{
    "published": "2015-11-10 07:30:23.853",
    "updated": "2015-11-10 07:30:23.853",
    "description": "おはようございます( ´ ▽ ` )ﾉ\n\n\nしぇからしか！を昨日沢山歌ったせいか\nずっと脳内でリピート再生されています。。。\n\n好きだ！好きだ！永遠に〜\n死ぬほど〜好きだよ、イエイイエイイエイ♪♪♪\n...",
    "content": "おはようございます( ´ ▽ ` )ﾉ<br /><br /><br />しぇからしか！を昨日沢山歌ったせいか<br />ずっと脳内でリピート再生されています。。。<br /><br />好きだ！好きだ！永遠に〜<br />死ぬほど〜好きだよ、イエイイエイイエイ♪♪♪<br /> <br /><br />直球だなぁ！！<br />いい歌！<br />綾小路翔さんのソロパートが癖になります。<br /><br />早く皆さんにも、フルで聴いてもらいたいです。<br />11月25日まで、待っていてください^o^<br /><br /><br />こんな直球に「好き」って言われると気持ちいいだろうなぁ！！<br /><br /><br />私は、皆さんのことが好きだーっ！！！！<br /><br /><br /><br />伝わっていますかー(｡-_-｡)？照<br /><br /><br />今日も、しぇからしか！の歌収録。<br />頑張るけん！！<br /><br /><br /><br /><br /><br /><br /><br />﻿",
    "url": "https://plus.google.com/111907069956262615426/posts/84ix7t76vdQ",
    "images": [
        "https://lh3.googleusercontent.com/-AimZ22rhHxQ/VkEeftvLP1I/AAAAAAAX2XE/yRdlL4sVf1Y/w960-h1280/10%2B-%2B1"
    ],
    "videos": []
}