{
    "published": "2015-08-07 17:57:27.421",
    "updated": "2015-08-07 17:57:27.421",
    "descript": "握手会終わりました＼(^o^)／\n\n\n今日の私服はこちら💕\n\n柄のトップスにレザーのタイトスカート。\n\n\n白コンバースのヒールシューズも最近お気に入りです。\n\n\n握手会、足を運んでくださった皆さんありがとう...",
    "content": "握手会終わりました＼(^o^)／<br /><br /><br />今日の私服はこちら💕<br /><br />柄のトップスにレザーのタイトスカート。<br /><br /><br />白コンバースのヒールシューズも最近お気に入りです。<br /><br /><br />握手会、足を運んでくださった皆さんありがとうございました！！<br /><br />感想待っとうけん🙉💓<br /><br />﻿",
    "url": "https://plus.google.com/111907069956262615426/posts/UnpSfLHHMr2",
    "images": [
        "https://lh3.googleusercontent.com/-7kNOq938HeE/VcSdJlmD3BI/AAAAAAAXtQI/SQzInJh2Bpw/w1280-h960/07%2B-%2B1"
    ]
}