{
    "published": "2015-01-01 00:04:22.341",
    "updated": "2015-01-01 00:04:22.341",
    "description": "あけましておめでとうございます🎊🎉\n\n\nNHK紅白歌合戦\nありがとうございました＼(^o^)／\n\n\n紅組、勝利はできませんでしたが\nどのアーティストさんも素晴らしい演出で\n私も、ずっと目を離せません...",
    "content": "あけましておめでとうございます🎊🎉<br /><br /><br />NHK紅白歌合戦<br />ありがとうございました＼(^o^)／<br /><br /><br />紅組、勝利はできませんでしたが<br />どのアーティストさんも素晴らしい演出で<br />私も、ずっと目を離せませんでした。<br /><br /><br />紅組がもし勝てなかったら<br />さっしーが滝行するって言ってたけど…笑<br /><br /><br />白組の皆さん<br />おめでとうございます。<br /><br /><br /><br />そして、HKT48は初出場。<br />トップバッターで『メロンジュース』を歌わせていただきました。<br /><br /><br /><br />今までにない、緊張感と高揚感を味わいながらのステージでしたが<br />博多から全国へを盛り上げたい！！<br />そんな思いを込めてメンバーと心を１つにして<br />パフォーマンスをしました。<br /><br /><br />全国、世界中の皆さんにこの想い伝わったかな？？<br /><br /><br /><br />まだまだ伝えたいこと沢山。<br />また、改めて書きたいと思います。<br /><br /><br />幸せな一年を過ごせたことに心から感謝。<br />良いお年を…<br /><br /><br />おやすみなさい☆<br />ぷひゅーはー（´-`）.｡oO（<br /><br />﻿",
    "url": "https://plus.google.com/111907069956262615426/posts/S71rsFNJR48",
    "images": [
        "https://lh3.googleusercontent.com/-k-w5yYm8mUo/VKQQdcY9M1I/AAAAAAAXX7Y/Nr1ZMS-8ktI/w750-h1000/IMG_2456.JPG"
    ],
    "videos": []
}