{
    "published": "2015-05-17 21:15:39.938",
    "updated": "2015-05-17 22:04:59.000",
    "description": "こんばんは( ´ ▽ ` )ﾉ\n兒玉遥です！！\n\n\n全国ツアーin島根県終わりましたー！！\n久しぶりにコンサートやったけど、やっぱり別格の楽しさ！！\n\n\nステージに立っている時の感覚が、1番好きです。...",
    "content": "こんばんは( ´ ▽ ` )ﾉ<br />兒玉遥です！！<br /><br /><br />全国ツアーin島根県終わりましたー！！<br />久しぶりにコンサートやったけど、やっぱり別格の楽しさ！！<br /><br /><br />ステージに立っている時の感覚が、1番好きです。<br /><br /><br />客席からの、歓声、応援。<br />うちわに、タオルにペンライト。<br />一つの会場に熱が集合している感じ。<br /><br />幸せなひと時でした。<br />今日が終わらなければいいのにって思いました！！<br /><br />今日は、いつもより、沢山<br />二階席や後ろの方までアイコンタクトできたがするなぁ☺️✨💕<br /><br /><br />届いていますように…<br /><br /><br /><br />来てくださった皆さん<br />ありがとうございました！！<br /><br />それと、みおちゃん17歳のお誕生おめでとう＼(^o^)／<br /><br />素敵な1年になりますように…<br /><br />おやすみなさい。<br />ぷひゅーはー（´-`）.｡oO（🌟﻿",
    "url": "https://plus.google.com/111907069956262615426/posts/bDzDSEfjASp",
    "images": [
        "https://lh3.googleusercontent.com/-gcJLHP14vek/VViGatPpW4I/AAAAAAAXlyk/sccKlkGplXc/w750-h1000/17%2B-%2B1"
    ],
    "videos": []
}