[
    {
        "text": "はるちゃんの王子様はどんな人が理想☺💓⁉",
        "trans": ""
    },
    {
        "text": "おじさま",
        "trans": ""
    },
    {
        "text": "「しあわせを分けなさい」のLong ver見ました❗\nブーケトスが取れなくて、悔しがってみーおんから1輪\nもらってるはるっぴが可愛いかった❗はるっぴから見て、\nさしこちゃんの結婚式、披露宴はどうでしたか？💒👰",
        "trans": ""
    },
    {
        "text": "結婚式羨ましかったです。\n待ってろ王子様！✨っておもいました。",
        "trans": ""
    },
    {
        "text": "二公演目おわり〜\n女の子多かった気がした😊😊😊\nありがとうございました！！！\n\n男の子もいっぱいたよ！！\nいよいよ、次でラスト！！\n",
        "trans": ""
    },
    {
        "text": "USJやり過ぎサマーシアター最終日！！",
        "trans": ""
    },
    {
        "text": "おはようございます(´∇｀)",
        "trans": ""
    }
]