{
    "id": "z12jud0gfvf0zvq3u22igtpxmpe0ipqcb",
    "published": "2012-04-23 07:48:30.842",
    "updated": "2012-04-23 07:48:30.842",
    "description": "おはよー\nごーざいますー\n\n\n今日は夢を見た。\n\n\nあれ？\n\n\n\n…なんだったっけ？\n\n夢ってすぐ忘れちゃう(>_<)\n\n\n\nどなたか\n知ってる方いらっしゃいませんか？",
    "content": "おはよー<br />ごーざいますー<br /><br /><br />今日は夢を見た。<br /><br /><br />あれ？<br /><br /><br /><br />…なんだったっけ？<br /><br />夢ってすぐ忘れちゃう(&gt;_&lt;)<br /><br /><br /><br />どなたか<br />知ってる方いらっしゃいませんか？<br /><br />﻿",
    "url": "https://plus.google.com/111907069956262615426/posts/MXJDH7kcYNS",
    "images": [],
    "videos": []
}