{
    "id": "z12mfj2hlvm1yrerl04cdtnarqepc1uqt0w",
    "published": "2014-05-09 07:57:14.192",
    "updated": "2014-05-09 07:57:14.192",
    "description": "おはようございましゅ！\n\nあれ？\n昨日のぷひゅーはー投稿送られてなかった；＿；）\n\n最近端末の調子悪い…\n\nごめんなさい！\n\n今日も元気に\n行ってきます♪\n\n\n\nこんばんはるっぴ♪\n\n\n今回、NOTTV...",
    "content": "おはようございましゅ！<br /><br />あれ？<br />昨日のぷひゅーはー投稿送られてなかった；＿；）<br /><br />最近端末の調子悪い…<br /><br />ごめんなさい！<br /><br />今日も元気に<br />行ってきます♪<br /><br /><br /><br />こんばんはるっぴ♪<br /><br /><br />今回、NOTTVで<br />HKT48の『ほかみな』～ほかのみなさん～の冠番組が決定しました！！！<br /><br /><br />初回は5月23日（火）23:00～だそうですヽ(´▽`)ﾉ<br /><br />私もどんな番組か詳しくは分からないのですが <br />とても楽しみです！<br /><br />HKT48のメンバーを知ってもらう<br />きっかけになったらなと思います(〃▽〃)<br /><br />そして、<br />チームK4のみんなお疲れ様！！！<br /><br />明日はチームHの『青春ガールズ』公演です。<br /><br />２回目。<br />緊張するなぁ…<br />頑張るけん！！<br /><br />おやすみなさい。<br />ぷひゅーはー☆彡﻿",
    "url": "https://plus.google.com/111907069956262615426/posts/hNFQudqaCc3",
    "images": [
        "https://lh4.googleusercontent.com/-KQd71urTcwk/U2wLyBw7HSI/AAAAAAATMJo/9m45CRKk5Tc/w960-h1280/09%2B-%2B1"
    ],
    "videos": []
}