{
    "id": "z13awtxieo3hczjo104cdtnarqepc1uqt0w",
    "published": "2013-02-23 22:29:58.393",
    "updated": "2013-02-23 22:29:58.393",
    "description": "この前、募集した質問に\n\n「はるっぴは前髪を全部下ろすとどうなりますか？」\n\nとあったので\n試しにやってみたら\n凄いことになってしまいました(๑°ﾛ °๑)驚\n\n皆さん見たいですか？",
    "content": "この前、募集した質問に<br /><br />「はるっぴは前髪を全部下ろすとどうなりますか？」<br /><br />とあったので<br />試しにやってみたら<br />凄いことになってしまいました(๑°ﾛ °๑)驚<br /><br />皆さん見たいですか？﻿",
    "url": "https://plus.google.com/111907069956262615426/posts/NfArfTJP9LY",
    "images": [],
    "videos": []
}