{
    "id": "z134cbbbtvrps5dn522igtpxmpe0ipqcb",
    "published": "2013-02-18 00:23:02.465",
    "updated": "2013-02-18 00:32:49.000",
    "description": "こんばんは。兒玉遥です＼(^o^)／\n\n\n千秋楽のことについて語りだすと\nきりがなくなりそうなので\n簡潔にまとめます。\n\n\n初日の頃\nは正直、歌もダンスも表現も下手で\n自分に自信がありませんでした。\n...",
    "content": "こんばんは。兒玉遥です＼(^o^)／<br /><br /><br />千秋楽のことについて語りだすと<br />きりがなくなりそうなので<br />簡潔にまとめます。<br /><br /><br />初日の頃<br />は正直、歌もダンスも表現も下手で<br />自分に自信がありませんでした。<br />特にglory daysは<br />SKE48松井珠理奈さんに作られたユニット曲だったので<br />ダンスの難易度が高くて<br />なかなか思うようにパフォーマンスができなくて<br />毎回、自分に納得できませんでした。<br /><br /><br />そこから約1年と3カ月この公演をしてきて<br />今日の私は、初日の自分とは違い<br />自信を持って堂々とパフォーマンスできたなって思います。<br /><br />この公演のおかげで<br />私としてもチームとしても<br />進化できました。<br /><br />「手をつなぎながら」公演<br />ありがとう。<br /><br /><br />そして、HKT48チームHの「手をつなぎながら<br />」公演も<br />愛してくださった皆さん。<br /><br />ありがとうございました。<br /><br /><br />また、3/1に始まる「博多レジェンド(仮)」公演で<br />皆さんの期待に応えられるように<br />チーム一丸となって<br />頑張っていこうと思います!!!<br /><br />あと少しやけん<br />楽しみにしとってねー(*^^)v<br /><br />おやすみなさい。<br />ぷひゅーはー✻❄﻿",
    "url": "https://plus.google.com/111907069956262615426/posts/Hwi5ayLj1Ww",
    "images": [
        "https://lh4.googleusercontent.com/-UTTyaNrvlb8/USD11cLiacI/AAAAAAAXObY/zcrgEvkNmT0/w960-h1280/17%2B-%2B1"
    ],
    "videos": []
}