{
    "id": "z122vrtbikmtclr1f22igtpxmpe0ipqcb",
    "published": "2014-02-13 22:41:46.928",
    "updated": "2014-02-13 22:41:46.928",
    "description": "こんばんは。兒玉遥です＼(^o^)／\n\n明日は、目標の1つだった\nMステ出演。\n\n全身全霊尽くす勢いで\n頑張るけん!(^^)!\n\nおやすみなさい。\nぷひゅーはー☆彡",
    "content": "こんばんは。兒玉遥です＼(^o^)／<br /><br />明日は、目標の1つだった<br />Mステ出演。<br /><br />全身全霊尽くす勢いで<br />頑張るけん!(^^)!<br /><br />おやすみなさい。<br />ぷひゅーはー☆彡﻿",
    "url": "https://plus.google.com/111907069956262615426/posts/8K8djFVjW9J",
    "images": [
        "https://lh3.googleusercontent.com/-l0L9tOWG7xU/UvzLmY7FVlI/AAAAAAAQH3A/M1irtrr9PDg/w240-h320/13%2B-%2B1"
    ],
    "videos": []
}