{
    "id": "z12fgvkbxzyuutc1e22igtpxmpe0ipqcb",
    "published": "2016-02-09 20:53:02.992",
    "updated": "2016-02-09 20:53:02.992",
    "description": "『音楽の力』\nこんばんは( ´ ▽ ` )ﾉ兒玉遥です！\n\n今日は、朝から夜まで\n音楽の力を借りて1日過ごしましたー！！\n\n今日わたしが力をいただいたのは\n大原櫻子さんです💓\n\n櫻子さんの好きな曲を...",
    "content": "『音楽の力』<br />こんばんは( ´ ▽ ` )ﾉ兒玉遥です！<br /><br />今日は、朝から夜まで<br />音楽の力を借りて1日過ごしましたー！！<br /><br />今日わたしが力をいただいたのは<br />大原櫻子さんです💓<br /><br />櫻子さんの好きな曲を選んだ<br />こだわりセットリストで朝から気分を上げて<br />夜まで1日中撮影をしていましたー！！<br /><br />かわいいドールフェイスから溢れる<br />力強い声に、メッセージ性の深い歌詞。<br /><br />いつも元気をもらっています^o^<br /><br />ないより、絶対聴いた方が頑張れるんです。<br />音楽の力ってすごい。<br />誰かを元気にできるって幸せなことですね。<br /><br />私たちも皆さんにとってそんな存在になっていたら嬉しいなぁ✨<br /><br /><br />写真は、同期のしなもんと。<br />ぁあ、しなもんのチョコブラウニーたべたいなぁ💕<br /><br /><br />おやすみなさい★﻿",
    "url": "https://plus.google.com/111907069956262615426/posts/84uSpdXPX2M",
    "images": [
        "https://lh3.googleusercontent.com/-bRnGcuIK7GE/VrnTHnzoqYI/AAAAAAAX4NM/tsE59PpIqLY/w1280-h960/9e773524-4d42-42d1-bd5c-8c4122680f56"
    ],
    "videos": []
}