{
    "id": "z12qvlbzfujoinhhj04cdtnarqepc1uqt0w",
    "published": "2014-07-05 18:17:47.215",
    "updated": "2014-07-05 19:13:27.000",
    "description": "握手会終わりました(^-^)\n\n１ヶ月ぶりだったけど\n皆さんが元気で私も嬉しかったです♪\n\nやっぱり握手会って最高。\n\nないとダメだね！\n\n来て下さった皆さん\n沢山の笑顔を\nありがとうございました。\n...",
    "content": "握手会終わりました(^-^)<br /><br />１ヶ月ぶりだったけど<br />皆さんが元気で私も嬉しかったです♪<br /><br />やっぱり握手会って最高。<br /><br />ないとダメだね！<br /><br />来て下さった皆さん<br />沢山の笑顔を<br />ありがとうございました。<br /><br /><br />今日の私服はこんな感じ(^o^)v<br /><br />デニムのパッチワークのワンピースに<br />この前のパンプスを合わせたよ！！<br /><br />すっかり夏だね。<br /><br />感想待っとうけん:-)﻿",
    "url": "https://plus.google.com/111907069956262615426/posts/WLoL9YjN1nt",
    "images": [
        "https://lh5.googleusercontent.com/-DfWB6seAyjQ/U7fCul3PVYI/AAAAAAAVnMU/mBf8xJt5Esk/w960-h1280/05%2B-%2B1"
    ],
    "videos": []
}