{
    "id": "z12kthbjfkbjgzc0k22igtpxmpe0ipqcb",
    "published": "2014-08-01 17:45:18.335",
    "updated": "2014-08-01 17:45:18.335",
    "description": "撮影してました＼(^o^)／\n\n「デジモノステーション」\nという雑誌の\nビジョメガネの特集です。\n\n\n編集部の方が\n私のショートカットを\n珍しいと、気に入ってくださったみたい…♪\n\n嬉しい。\n\n\nスタッフ...",
    "content": "撮影してました＼(^o^)／<br /><br />「デジモノステーション」<br />という雑誌の<br />ビジョメガネの特集です。<br /><br /> <br />編集部の方が<br />私のショートカットを<br />珍しいと、気に入ってくださったみたい…♪<br /><br />嬉しい。<br /><br /><br />スタッフさんがた<br />皆さん優しくて<br />温かい撮影現場でした。<br /><br /><br />撮影の現場も<br />団地の裏や公園と<br />いつもと違った雰囲気で<br />新鮮な気持ちで撮影できました！！<br /><br /><br />私も出来上がりが楽しみです！<br /><br /><br />8月25日発売。<br /><br /><br />よかったら是非<br />チェックしてみてね(^_^)/﻿",
    "url": "https://plus.google.com/111907069956262615426/posts/3ihAoHHZLik",
    "images": [
        "https://lh5.googleusercontent.com/-yn6NvMIdxkU/U9tTnE81dkI/AAAAAAAW7ao/FgRoGijoXrI/w379-h379-p/01%2B-%2B1",
        "https://lh6.googleusercontent.com/-fuJnRFVUu0k/U9tTnN9O7dI/AAAAAAAW7aw/stnDo3-HSiE/w126-h126-p/01%2B-%2B2",
        "https://lh3.googleusercontent.com/-x7-kdO_iZi0/U9tTnC9nSBI/AAAAAAAW7bE/J5zz8cKCkU4/w126-h126-p/01%2B-%2B3",
        "https://lh6.googleusercontent.com/-90Z18sl4OBE/U9tTnPIKhYI/AAAAAAAW7bQ/Dw7PvIFVDyo/w126-h126-p/01%2B-%2B4"
    ],
    "videos": []
}