{
    "id": "z12aut1b0lbljpjt122igtpxmpe0ipqcb",
    "published": "2013-10-26 17:05:45.521",
    "updated": "2013-10-26 17:05:45.521",
    "description": "ふーっ。気持ちよかったーヽ(´▽｀)/\n\n\n全身リンパマッサージ\n行ってました♡\n\n痩せてるというより\nちゃんと筋肉がある\n引き締まった身体になりたいな(｡･･｡)",
    "content": "ふーっ。気持ちよかったーヽ(´▽｀)/<br /><br /><br />全身リンパマッサージ<br />行ってました♡<br /><br />痩せてるというより<br />ちゃんと筋肉がある<br />引き締まった身体になりたいな(｡･･｡)﻿",
    "url": "https://plus.google.com/111907069956262615426/posts/6bzMYPUBknG",
    "images": [
        "https://lh4.googleusercontent.com/-zTN6D_CsOVw/Umt32NDQknI/AAAAAAAMKs4/NME2THPmiZw/w768-h1024/26%2B-%2B1"
    ],
    "videos": []
}