{
    "id": "z125utf5prjmcx3zq04cdtnarqepc1uqt0w",
    "published": "2013-05-10 18:12:48.205",
    "updated": "2013-05-10 18:13:16.000",
    "description": "小林よしのりさんと対談してました＼(^o^)／\n\n初めての対談で緊張しましたが\nとてもHappyな対談になりました!!\n\n楽しかった(*˙˘˙)\n\n\n5月末発売の『ブブカ』に掲載されるけん♪\n\nチェック...",
    "content": "小林よしのりさんと対談してました＼(^o^)／<br /><br />初めての対談で緊張しましたが<br />とてもHappyな対談になりました!!<br /><br />楽しかった(*˙˘˙)<br /><br /><br />5月末発売の『ブブカ』に掲載されるけん♪<br /><br />チェック宜しくねー。﻿",
    "url": "https://plus.google.com/111907069956262615426/posts/iAevHmn7Msg",
    "images": [
        "https://lh4.googleusercontent.com/-nkFQF8FjI2M/UYy6D8C4OwI/AAAAAAAXO5E/k9_vHgpqw5Q/w960-h1280/10%2B-%2B1"
    ],
    "videos": []
}