{
    "id": "z13rsldzxpnkj5wow04cdtnarqepc1uqt0w",
    "published": "2013-03-09 13:14:54.722",
    "updated": "2013-03-09 17:37:29.000",
    "description": "こんにちは。\n\n\n3/20のCDデビューの日が近づいてきて\nドキドキワクワクした気持ちを\n隠しきれませんが\nこの日を忘れてはいけません。\n\n３月11日。\n\n私の住んでいる九州の博多は\n被災地から離れてい...",
    "content": "こんにちは。<br /><br /><br />3/20のCDデビューの日が近づいてきて<br />ドキドキワクワクした気持ちを<br />隠しきれませんが<br />この日を忘れてはいけません。<br /><br />３月11日。<br /><br />私の住んでいる九州の博多は<br />被災地から離れていて<br />直接見たり感じたりする機会が少ないです。<br /><br />だからこそ、私達、私が支援活動を通して<br />何か少しでも役にたてるなら<br />これからも続けたいと思っています。<br /><br />そして、AKB48の新たな<br />震災復興応援ソングである<br />『掌が語ること』の無料配信が開始されました。<br />この曲には、被災された方々を想い<br />気持ちを繋げて、<br />世界を一つになるように<br />という願いが込められています。<br /><br />私もダウンロードしたのですが<br />とても心が落ち着いて<br />これからも頑張ろうと思える<br />素敵な曲でした。<br /><br />皆さんも是非チェックしてみてください(<b>˘︶˘</b>)<br /><br /><br /><a href=\"http://www.akb48.co.jp/darekanotameni/\">http://www.akb48.co.jp/darekanotameni/</a><br /><br />﻿",
    "url": "https://plus.google.com/111907069956262615426/posts/TF71JfGngzJ",
    "images": [],
    "videos": []
}