{
    "id": "z12eerp4zt23g5nh204cdtnarqepc1uqt0w",
    "published": "2017-01-01 16:20:12.101",
    "updated": "2017-01-01 17:01:35.778",
    "description": "福岡ただいま！\n\nお母さんが「おかえり」って福岡空港で待っててくれました。\n\n\nそして、重い連泊の荷物を\nマネージャーさんとお母さん2人で持って車につめてくださいました。\n\n\nなみだがとまらなかった。...",
    "content": "福岡ただいま！<br /><br />お母さんが「おかえり」って福岡空港で待っててくれました。<br /><br /><br />そして、重い連泊の荷物を<br />マネージャーさんとお母さん2人で持って車につめてくださいました。<br /><br /><br />なみだがとまらなかった。<br />うしろの見えない席に倒れ、メガネをかけて、帽子を深くかぶり、マフラーで顔を覆った。<br /><br />でも、お母さんには隠せませんでした。<br /><br />すぐ見抜かれちゃうの。<br />だから、全部話しました。<br />頭の中にあるすべてを。<br /><br />ずっーと泣きながらお母さんに夢を語って、、、<br /><br /><br />信じている人には、お話できるけど<br />私、こわくておしゃべりできないの。<br /><br /><br />あれ？なんで泣いてるんだっけ？<br />分からないから、もう、おしまい。<br /><br /><br />みなさんからの、きもち。<br />ちゃーんと届いています！！<br />２９位、本当にありがとうございます。<br /><br /><br />紅白という夢の舞台にわたしがいるのは、<br />歌を唄えるのは<br />見守ってくださる誰かのおかげです。<br /><br />大切なことにきづけました。<br /><br />「Happy！new year！」と🎊<br />みんなが笑顔で新年を迎えられたから、私はしあわせです。<br /><br /><br />さや姉さんの後ろ姿が、かっよくて、眩しかった。夢をのせて羽ばたくとりのように、、、、⭐️<br /><br /><br />そして、だいすきなお母さんの料理たべたよ＼(^^)／<br /><br /><br />1番に、肉を！！29！！<br />元気でました。<br /><br /><br />今日は、ゆっくりやすもう<br /><br /><br /><br /><br />﻿",
    "url": "https://plus.google.com/111907069956262615426/posts/UCUipf3rMJb",
    "images": [],
    "videos": []
}