{
    "id": "z13xx3woatyacnmsd22igtpxmpe0ipqcb",
    "published": "2014-03-11 22:07:11.430",
    "updated": "2014-03-11 22:10:57.000",
    "description": "東日本大震災復興支援特別公演\n「誰かのために」プロジェクト~2014~\n終わりました。\n\n腰の痛みが残っていたのですが\n被災地された方々への想いが届けられるなら\n皆さんの笑顔ををみられるなら\n少しでも...",
    "content": "東日本大震災復興支援特別公演<br />「誰かのために」プロジェクト~2014~<br />終わりました。<br /><br />腰の痛みが残っていたのですが<br />被災地された方々への想いが届けられるなら<br />皆さんの笑顔ををみられるなら<br />少しでも役に立ちたいと思い<br />一部出演とさせていただきました！！<br /><br />公演では、上手く伝えられなくて<br />すいません(´ｰ｀)<br /><br />でも、快調に回復にしていってるので<br />心配しないでください！<br /><br />公演前後での募金活動では、<br />沢山の方が参加してくださって<br />福岡の皆さん復興への想いが感じれて<br />とても嬉しかったです。<br /><br />皆さんから頂いた募金は全額<br />赤十字を通して被災地方に<br />寄付させていただきます！<br /><br />本当にありがとうございました＼(^^)／<br /><br />私は、実は被災地に行って<br />特別公演に参加する予定だったのですが、<br />腰痛で行けなくなってしまいました。<br /><br />苦しかったです。<br />悔しかったです。<br /><br />前回、宮城県塩竈市に訪問させて頂いたとき<br />現地の方は今、どんな気持ちなのかな？<br />わたし達のライブで元気になってもらえるかな？<br />笑顔になってもらえるかな？って<br />正直、不安もありました。<br /><br />でも、実際にライブをしてみると<br />こんな表現は正しいか分かりませんが<br />震災の背景を感じさせないくらいの笑顔で<br />わたし達を迎えてくださいました。<br /><br />その情景を今でも忘れられません。<br /><br />その笑顔は、ものすごくパワーをもっているように感じました。<br /><br />心が温まって、ホッとして<br />こんな自分でも誰かのためになれるんだって<br />とても勇気づけられました。<br /><br />だから、次は<br />このお返しをしなきゃ<br />お礼しなきゃって思っていたのに…<br /><br />ごめんなさい。<br />こんな時に怪我しちゃって。<br /><br />私は、ステージに立って<br />皆さんの笑顔をみるのが大好きだし<br />それが私の生き甲斐なので<br />まずは、腰を治すことに集中したいと思います！<br /><br />そして<br />元気な、はるっぴになったら<br />絶対に被災地訪問したいし<br />また、あの笑顔のプレゼントを受取りたいです！<br /><br />待っていてください(^O^)<br /><br />東日本大震災による被災地の<br />より早い復興を願って<br />これからも活動を続けていきたいと思います。<br /><br />今、生きていることに感謝。<br /><br />                                                                                     兒玉 遥﻿",
    "url": "https://plus.google.com/111907069956262615426/posts/2c14Ky7Po8W",
    "images": [
        "https://lh4.googleusercontent.com/-Lts0MgTA_g8/Ux8KfQCbV2I/AAAAAAARHCw/4WLfShhZpDg/w960-h1280/11%2B-%2B1"
    ],
    "videos": []
}